odoo/addons/shopinvader_search_engine_update_product_media/README.rst
odoo/addons/shopinvader_search_engine_update_product_media/__init__.py
odoo/addons/shopinvader_search_engine_update_product_media/__manifest__.py
odoo/addons/shopinvader_search_engine_update_product_media/i18n/shopinvader_search_engine_update_product_media.pot
odoo/addons/shopinvader_search_engine_update_product_media/models/__init__.py
odoo/addons/shopinvader_search_engine_update_product_media/models/fs_product_media.py
odoo/addons/shopinvader_search_engine_update_product_media/readme/CONTEXT.md
odoo/addons/shopinvader_search_engine_update_product_media/readme/CONTRIBUTORS.md
odoo/addons/shopinvader_search_engine_update_product_media/readme/DESCRIPTION.md
odoo/addons/shopinvader_search_engine_update_product_media/static/description/icon.png
odoo/addons/shopinvader_search_engine_update_product_media/static/description/index.html
odoo/addons/shopinvader_search_engine_update_product_media/tests/__init__.py
odoo/addons/shopinvader_search_engine_update_product_media/tests/test_update.py
odoo_addon_shopinvader_search_engine_update_product_media-16.0.1.0.0.2.dist-info/METADATA
odoo_addon_shopinvader_search_engine_update_product_media-16.0.1.0.0.2.dist-info/WHEEL
odoo_addon_shopinvader_search_engine_update_product_media-16.0.1.0.0.2.dist-info/top_level.txt
odoo_addon_shopinvader_search_engine_update_product_media-16.0.1.0.0.2.dist-info/RECORD
