Metadata-Version: 2.1
Name: odoo-addon-shopinvader-search-engine-update-product-media
Version: 16.0.1.0.0.2
Summary: Shopinvader: Mark products linked to a media to be updated when the media change
Home-page: https://github.com/shopinvader/odoo-shopinvader
Author: ACSONE SA/NV,Odoo Community Association (OCA)
Author-email: support@odoo-community.org
License: AGPL-3
Platform: UNKNOWN
Classifier: Programming Language :: Python
Classifier: Framework :: Odoo
Classifier: Framework :: Odoo :: 16.0
Classifier: License :: OSI Approved :: GNU Affero General Public License v3
Classifier: Development Status :: 3 - Alpha
Requires-Python: >=3.10
Requires-Dist: odoo-addon-shopinvader-search-engine-product-media <16.1dev,>=16.0dev
Requires-Dist: odoo-addon-shopinvader-search-engine-update <16.1dev,>=16.0dev
Requires-Dist: odoo <16.1dev,>=16.0a
